MianxiangJisuanjiShijueDeShenduXuexiChuyi/README.md
MianxiangJisuanjiShijueDeShenduXuexiChuyi/__init__.py
MianxiangJisuanjiShijueDeShenduXuexiChuyi/__main__.py
MianxiangJisuanjiShijueDeShenduXuexiChuyi/file.epub
MianxiangJisuanjiShijueDeShenduXuexiChuyi/index.html
MianxiangJisuanjiShijueDeShenduXuexiChuyi/css/__init__.py
MianxiangJisuanjiShijueDeShenduXuexiChuyi/css/annotations.css
MianxiangJisuanjiShijueDeShenduXuexiChuyi/css/main.css
MianxiangJisuanjiShijueDeShenduXuexiChuyi/css/normalize.css
MianxiangJisuanjiShijueDeShenduXuexiChuyi/css/popup.css
MianxiangJisuanjiShijueDeShenduXuexiChuyi/font/__init__.py
MianxiangJisuanjiShijueDeShenduXuexiChuyi/font/fontello.eot
MianxiangJisuanjiShijueDeShenduXuexiChuyi/font/fontello.svg
MianxiangJisuanjiShijueDeShenduXuexiChuyi/font/fontello.ttf
MianxiangJisuanjiShijueDeShenduXuexiChuyi/font/fontello.woff
MianxiangJisuanjiShijueDeShenduXuexiChuyi/img/__init__.py
MianxiangJisuanjiShijueDeShenduXuexiChuyi/img/annotator-glyph-sprite.png
MianxiangJisuanjiShijueDeShenduXuexiChuyi/img/annotator-icon-sprite.png
MianxiangJisuanjiShijueDeShenduXuexiChuyi/img/apple-touch-icon.png
MianxiangJisuanjiShijueDeShenduXuexiChuyi/img/cancelfullscreen.png
MianxiangJisuanjiShijueDeShenduXuexiChuyi/img/close.png
MianxiangJisuanjiShijueDeShenduXuexiChuyi/img/fullscreen.png
MianxiangJisuanjiShijueDeShenduXuexiChuyi/img/loader.gif
MianxiangJisuanjiShijueDeShenduXuexiChuyi/img/menu-icon.png
MianxiangJisuanjiShijueDeShenduXuexiChuyi/img/save.png
MianxiangJisuanjiShijueDeShenduXuexiChuyi/img/saved.png
MianxiangJisuanjiShijueDeShenduXuexiChuyi/img/settings-s.png
MianxiangJisuanjiShijueDeShenduXuexiChuyi/img/settings.png
MianxiangJisuanjiShijueDeShenduXuexiChuyi/img/star.png
MianxiangJisuanjiShijueDeShenduXuexiChuyi/js/__init__.py
MianxiangJisuanjiShijueDeShenduXuexiChuyi/js/epub.js
MianxiangJisuanjiShijueDeShenduXuexiChuyi/js/epub.min.js
MianxiangJisuanjiShijueDeShenduXuexiChuyi/js/epub.min.map
MianxiangJisuanjiShijueDeShenduXuexiChuyi/js/hooks.min.js
mianxiang_jisuanji_shijue_de_shendu_xuexi_chuyi-2024.3.5.0.dist-info/METADATA
mianxiang_jisuanji_shijue_de_shendu_xuexi_chuyi-2024.3.5.0.dist-info/WHEEL
mianxiang_jisuanji_shijue_de_shendu_xuexi_chuyi-2024.3.5.0.dist-info/entry_points.txt
mianxiang_jisuanji_shijue_de_shendu_xuexi_chuyi-2024.3.5.0.dist-info/top_level.txt
mianxiang_jisuanji_shijue_de_shendu_xuexi_chuyi-2024.3.5.0.dist-info/RECORD
